trytond/modules/health_pediatrics_growth_charts_who/COPYING
trytond/modules/health_pediatrics_growth_charts_who/README.rst
trytond/modules/health_pediatrics_growth_charts_who/__init__.py
trytond/modules/health_pediatrics_growth_charts_who/data/bmi_boys_p.xml
trytond/modules/health_pediatrics_growth_charts_who/data/bmi_boys_z.xml
trytond/modules/health_pediatrics_growth_charts_who/data/bmi_girls_p.xml
trytond/modules/health_pediatrics_growth_charts_who/data/bmi_girls_z.xml
trytond/modules/health_pediatrics_growth_charts_who/data/lhfa_boys_p.xml
trytond/modules/health_pediatrics_growth_charts_who/data/lhfa_boys_z.xml
trytond/modules/health_pediatrics_growth_charts_who/data/lhfa_girls_p.xml
trytond/modules/health_pediatrics_growth_charts_who/data/lhfa_girls_z.xml
trytond/modules/health_pediatrics_growth_charts_who/data/messages/messages.xml
trytond/modules/health_pediatrics_growth_charts_who/data/wfa_boys_p.xml
trytond/modules/health_pediatrics_growth_charts_who/data/wfa_boys_z.xml
trytond/modules/health_pediatrics_growth_charts_who/data/wfa_girls_p.xml
trytond/modules/health_pediatrics_growth_charts_who/data/wfa_girls_z.xml
trytond/modules/health_pediatrics_growth_charts_who/health_pediatrics_growth_charts_who.py
trytond/modules/health_pediatrics_growth_charts_who/health_pediatrics_growth_charts_who_report.xml
trytond/modules/health_pediatrics_growth_charts_who/health_pediatrics_growth_charts_who_view.xml
trytond/modules/health_pediatrics_growth_charts_who/locale/ar.po
trytond/modules/health_pediatrics_growth_charts_who/locale/de.po
trytond/modules/health_pediatrics_growth_charts_who/locale/el.po
trytond/modules/health_pediatrics_growth_charts_who/locale/eo.po
trytond/modules/health_pediatrics_growth_charts_who/locale/es.po
trytond/modules/health_pediatrics_growth_charts_who/locale/fr.po
trytond/modules/health_pediatrics_growth_charts_who/locale/health_pediatrics_growth_charts_who.pot
trytond/modules/health_pediatrics_growth_charts_who/locale/it_IT.po
gnuhealth_pediatrics_growth_charts_who-5.0.2.dist-info/METADATA
gnuhealth_pediatrics_growth_charts_who-5.0.2.dist-info/WHEEL
gnuhealth_pediatrics_growth_charts_who-5.0.2.dist-info/licenses/COPYING
gnuhealth_pediatrics_growth_charts_who-5.0.2.dist-info/RECORD
